BlitzTUI-0.48.1.dist-info/DESCRIPTION.rst
BlitzTUI-0.48.1.dist-info/METADATA
BlitzTUI-0.48.1.dist-info/RECORD
BlitzTUI-0.48.1.dist-info/WHEEL
BlitzTUI-0.48.1.dist-info/entry_points.txt
BlitzTUI-0.48.1.dist-info/metadata.json
BlitzTUI-0.48.1.dist-info/top_level.txt
blitztui/__init__.py
blitztui/client.py
blitztui/file_logger.py
blitztui/file_watcher.py
blitztui/main.py
blitztui/memo.py
blitztui/version.py
blitztui/ui/__init__.py
blitztui/ui/home.py
blitztui/ui/invoice.py
blitztui/ui/off.py
blitztui/ui/qcode.py
blitztui/ui/resources_rc.py
