Metadata-Version: 2.0
Name: BlitzTUI
Version: 0.48.1
Summary: Touch User Interface for RaspiBlitz
Home-page: https://github.com/rootzoll/raspiblitz
Author: RaspiBlitz Developers
Author-email: raspiblitz@rhab.de
License: UNKNOWN
Platform: UNKNOWN
Classifier: Development Status :: 4 - Beta
Classifier: Programming Language :: Python :: 3
Classifier: License :: OSI Approved :: MIT License
Classifier: Operating System :: POSIX :: Linux
Requires-Python: >=3.4
Requires-Dist: googleapis-common-protos
Requires-Dist: grpcio
Requires-Dist: inotify
Requires-Dist: psutil
Requires-Dist: pyqtspinner
Requires-Dist: qrcode
